pySQLExport_gui/__init__.py
pySQLExport_gui/__main__.py
pySQLExport_gui/database.py
pySQLExport_gui/database_mysql.py
pySQLExport_gui/database_pgsql.py
pySQLExport_gui/main_window.py
pySQLExport_gui/new_connection_window.py
pySQLExport_gui/pySQLExport.py
pySQLExport_gui-1.0.dist-info/LICENSE
pySQLExport_gui-1.0.dist-info/METADATA
pySQLExport_gui-1.0.dist-info/WHEEL
pySQLExport_gui-1.0.dist-info/entry_points.txt
pySQLExport_gui-1.0.dist-info/top_level.txt
pySQLExport_gui-1.0.dist-info/RECORD
