Metadata-Version: 2.1
Name: pySQLExport-gui
Version: 1.0
Summary: A GUI application for exporting SQL query results into csv, json, xml, html, excel, and muck more.
Home-page: https://github.com/yourusername/pySQLExport-gui
Author: Aaron Mathis
Author-email: aaron.mathis@gmail.com
Classifier: Programming Language :: Python :: 3
Classifier: License :: OSI Approved :: GNU General Public License v3 (GPLv3)
Classifier: Operating System :: OS Independent
Requires-Python: >=3.6
License-File: LICENSE
Requires-Dist: PyQt6
Requires-Dist: mysql-connector-python
Requires-Dist: pandas
Requires-Dist: psycopg2-binary
Requires-Dist: fastparquet
Requires-Dist: numpy
Requires-Dist: tables
